Backtester_Tushar/__init__.py
Backtester_Tushar/code_checker.py
Backtester_Tushar/consolidated.py
Backtester_Tushar/example.py
Backtester_Tushar/setup.py
Backtester_Tushar/test.py
Backtester_Tushar/Data/__init__.py
Backtester_Tushar/Data/connector.py
Backtester_Tushar/Data/handler.py
Backtester_Tushar/Data/utils.py
Backtester_Tushar/Execution/__init__.py
Backtester_Tushar/Execution/execution_model.py
Backtester_Tushar/Execution/t_cost.py
Backtester_Tushar/Feature_Generator/__init__.py
Backtester_Tushar/Feature_Generator/feature_gen.py
Backtester_Tushar/Feature_Generator/market_regime_feature.py
Backtester_Tushar/Feature_Generator/sarimax_feature.py
Backtester_Tushar/Feature_Generator/utils.py
Backtester_Tushar/Portfolio_Management_and_Tracker/__init__.py
Backtester_Tushar/Portfolio_Management_and_Tracker/analyzer.py
Backtester_Tushar/Portfolio_Management_and_Tracker/new.py
Backtester_Tushar/Portfolio_Management_and_Tracker/portfolio_level_backtest.py
Backtester_Tushar/Portfolio_Management_and_Tracker/portfolio_management.py
Backtester_Tushar/Portfolio_Management_and_Tracker/tracker.py
Backtester_Tushar/Portfolio_Management_and_Tracker/utils.py
Backtester_Tushar/Portfolio_Opt/__init__.py
Backtester_Tushar/Portfolio_Opt/optimization.py
Backtester_Tushar/Risk/__init__.py
Backtester_Tushar/Risk/risk_limits.py
Backtester_Tushar/Risk/risk_manager.py
Backtester_Tushar/Sizing/__init__.py
Backtester_Tushar/Sizing/atr_based_sizing.py
Backtester_Tushar/Sizing/base_class.py
Backtester_Tushar/Sizing/portfolio_weights.py
Backtester_Tushar/Strategy/__init__.py
Backtester_Tushar/Strategy/base_class.py
Backtester_Tushar/Strategy/ml_base_class.py
Backtester_Tushar/Strategy/signal_processing.py
Backtester_Tushar/Strategy/utils.py
Backtester_Tushar/Strategy/All_Strategies/__init__.py
Backtester_Tushar/Strategy/All_Strategies/Ensemble_Strategy/__init__.py
Backtester_Tushar/Strategy/All_Strategies/Ensemble_Strategy/ensemble_strategy.py
backtester_tushar-0.5.2.dist-info/METADATA
backtester_tushar-0.5.2.dist-info/WHEEL
backtester_tushar-0.5.2.dist-info/top_level.txt
backtester_tushar-0.5.2.dist-info/RECORD
