Metadata-Version: 2.4
Name: Backtester_Tushar
Version: 0.5.2
Summary: Backtesting Package
Home-page: https://github.com/tusharsarkar3/Backtester_Tushar
Author: Tushar Sarkar
Author-email: tusharsarkar866@gmail.com
Classifier: Programming Language :: Python :: 3
Classifier: License :: OSI Approved :: MIT License
Classifier: Operating System :: OS Independent
Dynamic: author
Dynamic: author-email
Dynamic: classifier
Dynamic: description
Dynamic: description-content-type
Dynamic: home-page
Dynamic: summary
